mpl_gui/__init__.py
mpl_gui/_creation.py
mpl_gui/_figure.py
mpl_gui/_manage_backend.py
mpl_gui/_manage_interactive.py
mpl_gui/_promotion.py
mpl_gui/_version.py
mpl_gui/_patched_backends/__init__.py
mpl_gui/_patched_backends/tkagg.py
mpl_gui/tests/__init__.py
mpl_gui/tests/conftest.py
mpl_gui/tests/test_examples.py
mpl_gui-0.0.1.dist-info/AUTHORS.rst
mpl_gui-0.0.1.dist-info/LICENSE
mpl_gui-0.0.1.dist-info/METADATA
mpl_gui-0.0.1.dist-info/WHEEL
mpl_gui-0.0.1.dist-info/entry_points.txt
mpl_gui-0.0.1.dist-info/top_level.txt
mpl_gui-0.0.1.dist-info/RECORD
