Metadata-Version: 2.1
Name: mpl-gui
Version: 0.0.1
Summary: Prototype project for splitting pyplot in half
Home-page: https://github.com/tacaswell/mpl-gui
Author: Thomas A Caswell
Author-email: tcaswell@gmail.com
License: BSD (3-clause)
Platform: UNKNOWN
Classifier: Development Status :: 2 - Pre-Alpha
Classifier: Natural Language :: English
Classifier: Programming Language :: Python :: 3
Requires-Python: >=3.7
License-File: LICENSE
License-File: AUTHORS.rst
Requires-Dist: matplotlib
